AtomicTrit/__init__.py
AtomicTrit/constants.py
AtomicTrit/dipolelosses.py
AtomicTrit/elastic.py
AtomicTrit/hyperfine.py
AtomicTrit/potentials.py
AtomicTrit/spinbasis.py
AtomicTrit/spinexchange.py
AtomicTrit/InputData/.DS_Store
AtomicTrit/InputData/AdiabaticCorrection_Kolos.xlsx
AtomicTrit/InputData/AdiabaticSingletCorrection_Pachuki2014.csv
AtomicTrit/InputData/AdiabaticSingletCorrection_Wolniewicz1993.csv
AtomicTrit/InputData/AdiabaticTripletCorrection_Kolos1990.csv
AtomicTrit/InputData/Singlet_Jamieson2000.csv
AtomicTrit/InputData/Singlet_Kolos1965.csv
AtomicTrit/InputData/Singlet_Kolos1974.csv
AtomicTrit/InputData/Singlet_Kolos1975.csv
AtomicTrit/InputData/Singlet_Wolniewicz1993.csv
AtomicTrit/InputData/Triplet_Jamieson2000.csv
AtomicTrit/InputData/Triplet_Kolos1965.csv
AtomicTrit/InputData/Triplet_Kolos1974.csv
AtomicTrit/InputData/.ipynb_checkpoints/Singlet_Jamieson2000-checkpoint.csv
AtomicTrit/InputData/.ipynb_checkpoints/Singlet_Kolos1965-checkpoint.csv
AtomicTrit/InputData/.ipynb_checkpoints/Singlet_Wolniewicz1993-checkpoint.csv
AtomicTrit/InputData/.ipynb_checkpoints/Triplet_Jamieson2000-checkpoint.csv
AtomicTrit/LitReview/.gitkeep
AtomicTrit/LitReview/Al_Maaitah_EX.json
AtomicTrit/LitReview/Stoof_Exchange_Channels_dd2aa_dd2ad_Mag.json
AtomicTrit/LitReview/Stoof_aa_ad.json
AtomicTrit/LitReview/Stoof_dd2ac_Mag.json
AtomicTrit/LitReview/Stoof_dd2cc_dd2cd_Mag.json
AtomicTrit/LitReview/Zygelman_Hydrogen_dd2aa.json
AtomicTrit/LitReview/Zygelman_Hydrogen_dd2ad.json
AtomicTrit/LitReview/Zygelman_Tritium_dd2aa.json
AtomicTrit/LitReview/Zygelman_Tritium_dd2ad.json
atomictrit-2.0.0.dist-info/licenses/LICENSE
atomictrit-2.0.0.dist-info/METADATA
atomictrit-2.0.0.dist-info/WHEEL
atomictrit-2.0.0.dist-info/top_level.txt
atomictrit-2.0.0.dist-info/RECORD
