Metadata-Version: 2.4
Name: AtomicTrit
Version: 2.0.0
Summary: Tools for calculating the scattering cross sections of atomic tritium and hydrogen for Project 8 and similar experiments
Home-page: https://github.com/UTA-NURES/AtomicTritScattering
Author: Ben Jones and Morgan Elliott
Author-email: Ben Jones <ben.jones@uta.edu>, Morgan Elliott <morgan.elliott@uta.edu>
License-Expression: MIT
Project-URL: Homepage, https://github.com/UTA-NURES/AtomicTrit
Project-URL: Issues, https://github.com/UTA-NURES/AtomicTrit/issues
Classifier: Programming Language :: Python :: 3
Classifier: Operating System :: OS Independent
Requires-Python: >=3.7, <4
License-File: LICENSE
Dynamic: author
Dynamic: home-page
Dynamic: license-file
Dynamic: requires-python
